{"color": "#FF3300","children": [{"color": "#FFFF00","children": [{"color": "#FFFF00","children": [{"color": "#CCCCCC","children": [{"color": "#FF3300","name": "RFC0278","title": "Revision of the Mail Box Protocol"},{"color": "#FF3300","name": "RFC0080","title": "Protocols and Data Formats"},{"color": "#FF3300","name": "RFC0227","title": "Data transfer rates (Rand\/UCLA)"},{"color": "#FF3300","name": "RFC0078","title": "NCP Status Report: UCSB\/Rand"},{"color": "#FF3300","name": "RFC0083","title": "Language-machine for data reconfiguration"},{"color": "#FF3300","name": "RFC0166","title": "Data Reconfiguration Service: An implementation specification"},{"color": "#FF3300","name": "RFC0040","title": "More Comments on the Forthcoming Protocol"},{"color": "#FF3300","name": "RFC0131","title": "Response to RFC 116: May NWG meeting"},{"color": "#FF3300","name": "RFC0141","title": "Comments on RFC 114: A File Transfer Protocol"},{"color": "#FF3300","name": "RFC0039","title": "Comments on Protocol Re: NWG\/RFC #36"},{"color": "#FF3300","name": "RFC0130","title": "Response to RFC 111: Pressure from the chairman"}],"name": "group0"},{"color": "#CCCCCC","children": [{"color": "#FF3300","name": "RFC0039","title": "Comments on Protocol Re: NWG\/RFC #36"}],"name": "group1"}],"name": "J.F. Heafner"}],"name": "authors"},{"color": "#CCCC99","children": [{"color": "#FF6600","children": [{"color": "#CCCC99","name": "RFC0111","title": "Pressure from the Chairman"}],"name": "updatedBy"}],"name": "updated"}],"name": "RFC0130","title": "Response to RFC 111: Pressure from the chairman"}