{"color": "#FF3300","children": [{"color": "#FFFF00","children": [{"color": "#FFFF00","children": [{"color": "#CCCCCC","children": [{"color": "#FF3300","name": "RFC1017","title": "Network requirements for scientific research: Internet task force on scientific computing"},{"color": "#FF3300","name": "RFC1124","title": "Policy issues in interconnecting networks"},{"color": "#FF3300","name": "RFC1077","title": "Critical issues in high bandwidth networking"},{"color": "#FF3300","name": "RFC1015","title": "Implementation plan for interagency research Internet"}],"name": "group0"}],"name": "B.M. Leiner"}],"name": "authors"}],"name": "RFC1077","title": "Critical issues in high bandwidth networking"}