{"color": "#FF3300","children": [{"color": "#FFFF00","children": [{"color": "#FFFF00","children": [{"color": "#CCCCCC","children": [{"color": "#FF3300","name": "RFC1526","title": "Assignment of System Identifiers for TUBA\/CLNP Hosts"},{"color": "#FF3300","name": "RFC1545","title": "FTP Operation Over Big Address Records (FOOBAR)"},{"color": "#FF3300","name": "RFC2332","title": "NBMA Next Hop Resolution Protocol (NHRP)"},{"color": "#FF3300","name": "RFC1561","title": "Use of ISO CLNP in TUBA Environments"},{"color": "#FF3300","name": "RFC1639","title": "FTP Operation Over Big Address Records (FOOBAR)(172)"},{"color": "#FF3300","name": "RFC1209","title": "The Transmission of IP Datagrams over the SMDS Service"}],"name": "group0"}],"name": "D. Piscitello"}],"name": "authors"}],"name": "RFC1526","title": "Assignment of System Identifiers for TUBA\/CLNP Hosts"}