{"color": "#FF3300","children": [{"color": "#FFFF00","children": [{"color": "#FFFF00","children": [{"color": "#CCCCCC","children": [{"color": "#FF3300","name": "RFC1149","title": "Standard for the transmission of IP datagrams on avian carriers"},{"color": "#FF3300","name": "RFC1073","title": "Telnet window size option"},{"color": "#FF3300","name": "RFC1075","title": "Distance Vector Multicast Routing Protocol"},{"color": "#FF3300","name": "RFC2549","title": "IP over Avian Carriers with Quality of Service"}],"name": "group0"}],"name": "D. Waitzman"},{"color": "#FFFF00","children": [{"color": "#CCCCCC","children": [{"color": "#FF3300","name": "RFC1021","title": "High-level Entity Management System (HEMS)"},{"color": "#FF3300","name": "RFC2309","title": "Recommendations on Queue Management and Congestion Avoidance in the Internet"},{"color": "#FF3300","name": "RFC1152","title": "Workshop report: Internet research steering group workshop on very-high-speed networks"},{"color": "#FF3300","name": "RFC2075","title": "IP Echo Host Service"},{"color": "#FF3300","name": "RFC1546","title": "Host Anycasting Service"},{"color": "#FF3300","name": "RFC1257","title": "Isochronous applications do not require jitter-controlled networks"},{"color": "#FF3300","name": "RFC1071","title": "Computing the Internet checksum"},{"color": "#FF3300","name": "RFC1063","title": "IP MTU discovery options"},{"color": "#FF3300","name": "RFC1363","title": "A Proposed Flow Specification"},{"color": "#FF3300","name": "RFC1146","title": "TCP alternate checksum options(107)"},{"color": "#FF3300","name": "RFC2414","title": "Increasing TCP's Initial Window"}],"name": "group0"},{"color": "#CCCCCC","children": [{"color": "#FF3300","name": "RFC1146","title": "TCP alternate checksum options(107)"}],"name": "group1"}],"name": "C. Partridge"},{"color": "#FFFF00","children": [{"color": "#CCCCCC","children": [{"color": "#FF3300","name": "RFC1054","title": "Host extensions for IP multicasting(93)"},{"color": "#FF3300","name": "RFC0988","title": "Host extensions for IP multicasting"},{"color": "#FF3300","name": "RFC0966","title": "Host groups: A multicast extension to the Internet Protocol"},{"color": "#FF3300","name": "RFC1191","title": "Path MTU discovery"},{"color": "#FF3300","name": "RFC1075","title": "Distance Vector Multicast Routing Protocol"},{"color": "#FF3300","name": "RFC1112","title": "Host extensions for IP multicasting(101)"}],"name": "group0"}],"name": "S.E. Deering"}],"name": "authors"}],"name": "RFC1075","title": "Distance Vector Multicast Routing Protocol"}