{"color": "#FF3300","children": [{"color": "#FFFF00","children": [{"color": "#FFFF00","children": [{"color": "#CCCCCC","children": [{"color": "#FF3300","name": "RFC3760","title": "Securely Available Credentials (SACRED) - Credential Server Framework"},{"color": "#FF3300","name": "RFC3739","title": "Internet X.509 Public Key Infrastructure: Qualified Certificates Profile"},{"color": "#FF3300","name": "RFC2808","title": "The SecurID(r) SASL Mechanism"},{"color": "#FF3300","name": "RFC2985","title": "PKCS #9: Selected Object Classes and Attribute Types Version 2.0"},{"color": "#FF3300","name": "RFC3546","title": "Transport Layer Security (TLS) Extensions"},{"color": "#FF3300","name": "RFC6063","title": "Dynamic Symmetric Key Provisioning Protocol (DSKPP)"},{"color": "#FF3300","name": "RFC4366","title": "Transport Layer Security (TLS) Extensions(592)"},{"color": "#FF3300","name": "RFC2986","title": "PKCS #10: Certification Request Syntax Specification Version 1.7"},{"color": "#FF3300","name": "RFC7292","title": "Editor(1268)"},{"color": "#FF3300","name": "RFC4231","title": "Identifiers and Test Vectors for HMAC-SHA-224, HMAC-SHA-256, HMAC-SHA-384, and HMAC-SHA-512"},{"color": "#FF3300","name": "RFC3039","title": "Internet X.509 Public Key Infrastructure Qualified Certificates Profile"}],"name": "group0"},{"color": "#CCCCCC","children": [{"color": "#FF3300","name": "RFC4231","title": "Identifiers and Test Vectors for HMAC-SHA-224, HMAC-SHA-256, HMAC-SHA-384, and HMAC-SHA-512"}],"name": "group1"}],"name": "M. Nystrom"},{"color": "#FFFF00","children": [{"color": "#CCCCCC","children": [{"color": "#FF3300","name": "RFC1424","title": "Privacy Enhancement for Internet Electronic Mail: Part IV: Key Certification and Related Services"},{"color": "#FF3300","name": "RFC2314","title": "PKCS #10: Certification Request Syntax Version 1.5"},{"color": "#FF3300","name": "RFC5208","title": "Public-Key Cryptography Standards (PKCS) #8: Private-Key Information Syntax Specification Version 1.2"},{"color": "#FF3300","name": "RFC4055","title": "Additional Algorithms and Identifiers for RSA Cryptography for use in the Internet X.509 Public Key Infrastructure Certificate and Certificate Revocation List (CRL) Profile"},{"color": "#FF3300","name": "RFC2313","title": "PKCS #1: RSA Encryption Version 1.5"},{"color": "#FF3300","name": "RFC2985","title": "PKCS #9: Selected Object Classes and Attribute Types Version 2.0"},{"color": "#FF3300","name": "RFC2898","title": "PKCS #5: Password-Based Cryptography Specification Version 2.0"},{"color": "#FF3300","name": "RFC3447","title": "Public-Key Cryptography Standards (PKCS) #1: RSA Cryptography Specifications Version 2.1"},{"color": "#FF3300","name": "RFC1319","title": "The MD2 Message-Digest Algorithm"},{"color": "#FF3300","name": "RFC2986","title": "PKCS #10: Certification Request Syntax Specification Version 1.7"},{"color": "#FF3300","name": "RFC5990","title": "Use of the RSA-KEM Key Transport Algorithm in the Cryptographic Message Syntax (CMS)"}],"name": "group0"},{"color": "#CCCCCC","children": [{"color": "#FF3300","name": "RFC2986","title": "PKCS #10: Certification Request Syntax Specification Version 1.7"}],"name": "group1"}],"name": "B. Kaliski"}],"name": "authors"},{"color": "#00FF00","children": [{"color": "#FF6600","children": [{"color": "#00FF00","name": "RFC2314","title": "PKCS #10: Certification Request Syntax Version 1.5"}],"name": "obsoleteBy"}],"name": "obsolete"},{"color": "#33CC99","children": [{"color": "#FF6600","children": [{"color": "#33CC99","name": "RFC5967","title": "The application\/pkcs10 Media Type"}],"name": "updated"}],"name": "updatedBy"}],"name": "RFC2986","title": "PKCS #10: Certification Request Syntax Specification Version 1.7"}