{"color": "#FF3300","children": [{"color": "#FFFF00","children": [{"color": "#FFFF00","children": [{"color": "#CCCCCC","children": [{"color": "#FF3300","name": "RFC2589","title": "Lightweight Directory Access Protocol (v3): Extensions for Dynamic Directory Services"},{"color": "#FF3300","name": "RFC2218","title": "A Common Schema for the Internet White Pages Service"}],"name": "group0"}],"name": "T. Genovese"},{"color": "#FFFF00","children": [{"color": "#CCCCCC","children": [{"color": "#FF3300","name": "RFC1943","title": "Building an X.500 Directory Service in the US"},{"color": "#FF3300","name": "RFC2218","title": "A Common Schema for the Internet White Pages Service"}],"name": "group0"}],"name": "B. Jennings"}],"name": "authors"}],"name": "RFC2218","title": "A Common Schema for the Internet White Pages Service"}