{"color": "#FF3300","children": [{"color": "#FFFF00","children": [{"color": "#FFFF00","children": [{"color": "#CCCCCC","children": [{"color": "#FF3300","name": "RFC5150","title": "Label Switched Path Stitching with Generalized Multiprotocol Label Switching Traffic Engineering (GMPLS TE)"},{"color": "#FF3300","name": "RFC4201","title": "Link Bundling in MPLS Traffic Engineering (TE)"},{"color": "#FF3300","name": "RFC7447","title": "Deprecation of BGP Entropy Label Capability Attribute"},{"color": "#FF3300","name": "RFC4761","title": "Editor(669)"},{"color": "#FF3300","name": "RFC3480","title": "Signalling Unnumbered Links in CR-LDP (Constraint-Routing Label Distribution Protocol)"},{"color": "#FF3300","name": "RFC4379","title": "Detecting Multi-Protocol Label Switched (MPLS) Data Plane Failures"},{"color": "#FF3300","name": "RFC4202","title": "Editor(551)"},{"color": "#FF3300","name": "RFC4203","title": "Editor(552)"},{"color": "#FF3300","name": "RFC6388","title": "Editor(1063)"},{"color": "#FF3300","name": "RFC4205","title": "Editor(554)"},{"color": "#FF3300","name": "RFC5786","title": "Advertising a Router's Local Addresses in OSPF Traffic Engineering (TE) Extensions"}],"name": "group0"},{"color": "#CCCCCC","children": [{"color": "#FF3300","name": "RFC4205","title": "Editor(554)"}],"name": "group1"}],"name": "K. Kompella"},{"color": "#FFFF00","children": [{"color": "#CCCCCC","children": [{"color": "#FF3300","name": "RFC4631","title": "Link Management Protocol (LMP) Management Information Base (MIB)(648)"},{"color": "#FF3300","name": "RFC4207","title": "Synchronous Optical Network (SONET)\/Synchronous Digital Hierarchy (SDH) Encoding for Link Management Protocol (LMP) Test Messages"},{"color": "#FF3300","name": "RFC4204","title": "Editor(553)"},{"color": "#FF3300","name": "RFC4209","title": "Editor(555)"},{"color": "#FF3300","name": "RFC4327","title": "Link Management Protocol (LMP) Management Information Base (MIB)"},{"color": "#FF3300","name": "RFC3936","title": "Procedures for Modifying the Resource reSerVation Protocol (RSVP)"},{"color": "#FF3300","name": "RFC4220","title": "Traffic Engineering Link Management Information Base"},{"color": "#FF3300","name": "RFC4426","title": "Editor(604)"},{"color": "#FF3300","name": "RFC4394","title": "A Transport Network View of the Link Management Protocol (LMP)"}],"name": "group0"}],"name": "J. Lang"}],"name": "authors"},{"color": "#CCCC99","children": [{"color": "#FF6600","children": [{"color": "#CCCC99","name": "RFC3209","title": "RSVP-TE: Extensions to RSVP for LSP Tunnels"},{"color": "#CCCC99","name": "RFC2205","title": "Editor(252)"}],"name": "updatedBy"}],"name": "updated"}],"name": "RFC3936","title": "Procedures for Modifying the Resource reSerVation Protocol (RSVP)"}