{"color": "#FF3300","children": [{"color": "#FFFF00","children": [{"color": "#FFFF00","children": [{"color": "#CCCCCC","children": [{"color": "#FF3300","name": "RFC3322","title": "Signaling Compression (SigComp) Requirements & Assumptions"},{"color": "#FF3300","name": "RFC3321","title": "Signaling Compression (SigComp) - Extended Operations"},{"color": "#FF3300","name": "RFC3320","title": "Signaling Compression (SigComp)"},{"color": "#FF3300","name": "RFC3095","title": "RObust Header Compression (ROHC): Framework and four profiles: RTP, UDP, ESP, and uncompressed"}],"name": "group0"}],"name": "H. Hannu"}],"name": "authors"}],"name": "RFC3322","title": "Signaling Compression (SigComp) Requirements & Assumptions"}