{"color": "#FF3300","children": [{"color": "#FFFF00","children": [{"color": "#FFFF00","children": [{"color": "#CCCCCC","children": [{"color": "#FF3300","name": "RFC3087","title": "Control of Service Context using SIP Request-URI"},{"color": "#FF3300","name": "RFC7522","title": "Security Assertion Markup Language (SAML) 2.0 Profile for OAuth 2.0 Client Authentication and Authorization Grants"},{"color": "#FF3300","name": "RFC3824","title": "Using E.164 numbers with the Session Initiation Protocol (SIP)"},{"color": "#FF3300","name": "RFC3428","title": "Editor(413)"},{"color": "#FF3300","name": "RFC6755","title": "An IETF URN Sub-Namespace for OAuth"},{"color": "#FF3300","name": "RFC7068","title": "Diameter Overload Control Requirements"},{"color": "#FF3300","name": "RFC7523","title": "JSON Web Token (JWT) Profile for OAuth 2.0 Client Authentication and Authorization Grants"},{"color": "#FF3300","name": "RFC4975","title": "Editor(728)"},{"color": "#FF3300","name": "RFC7521","title": "Assertion Framework for OAuth 2.0 Client Authentication and Authorization Grants"},{"color": "#FF3300","name": "RFC4662","title": "A Session Initiation Protocol (SIP) Event Notification Extension for Resource Lists"}],"name": "group0"}],"name": "B. Campbell"},{"color": "#FFFF00","children": [{"color": "#CCCCCC","children": [{"color": "#FF3300","name": "RFC5028","title": "A Telephone Number Mapping (ENUM) Service Registration for Instant Messaging (IM) Services"},{"color": "#FF3300","name": "RFC3842","title": "A Message Summary and Message Waiting Indication Event Package for the Session Initiation Protocol (SIP)"},{"color": "#FF3300","name": "RFC5333","title": "IANA Registration of Enumservices for Internet Calendaring"},{"color": "#FF3300","name": "RFC3911","title": "The Session Initiation Protocol (SIP) \"Join\" Header"},{"color": "#FF3300","name": "RFC4235","title": "Editor(561)"},{"color": "#FF3300","name": "RFC6447","title": "Filtering Location Notifications in the Session Initiation Protocol (SIP)"},{"color": "#FF3300","name": "RFC3891","title": "The Session Initiation Protocol (SIP) \"Replaces\" Header"},{"color": "#FF3300","name": "RFC5389","title": "Session Traversal Utilities for NAT (STUN)"},{"color": "#FF3300","name": "RFC3489","title": "STUN - Simple Traversal of User Datagram Protocol (UDP) Through Network Address Translators (NATs)"},{"color": "#FF3300","name": "RFC4976","title": "Relay Extensions for the Message Sessions Relay Protocol (MSRP)"},{"color": "#FF3300","name": "RFC5850","title": "Editor(949)"}],"name": "group0"},{"color": "#CCCCCC","children": [{"color": "#FF3300","name": "RFC4976","title": "Relay Extensions for the Message Sessions Relay Protocol (MSRP)"}],"name": "group1"}],"name": "R. Mahy"},{"color": "#FFFF00","children": [{"color": "#CCCCCC","children": [{"color": "#FF3300","name": "RFC4770","title": "Editor(671)"},{"color": "#FF3300","name": "RFC4787","title": "Editor(675)"},{"color": "#FF3300","name": "RFC5039","title": "The Session Initiation Protocol (SIP) and Spam"},{"color": "#FF3300","name": "RFC4904","title": "Representing Trunk Groups in tel\/sip Uniform Resource Identifiers (URIs)"},{"color": "#FF3300","name": "RFC5727","title": "Change Process for the Session Initiation Protocol (SIP) and the Real-time Applications and Infrastructure Area"},{"color": "#FF3300","name": "RFC5341","title": "The Internet Assigned Number Authority (IANA) tel Uniform Resource Identifier (URI) Parameter Registry"},{"color": "#FF3300","name": "RFC6940","title": "Editor(1187)"},{"color": "#FF3300","name": "RFC6216","title": "Editor(1023)"},{"color": "#FF3300","name": "RFC4474","title": "Enhancements for Authenticated Identity Management in the Session Initiation Protocol (SIP)"},{"color": "#FF3300","name": "RFC4976","title": "Relay Extensions for the Message Sessions Relay Protocol (MSRP)"},{"color": "#FF3300","name": "RFC4458","title": "Session Initiation Protocol (SIP) URIs for Applications such as Voicemail and Interactive Voice Response (IVR)"}],"name": "group0"},{"color": "#CCCCCC","children": [{"color": "#FF3300","name": "RFC4976","title": "Relay Extensions for the Message Sessions Relay Protocol (MSRP)"}],"name": "group1"}],"name": "C. Jennings"}],"name": "authors"}],"name": "RFC4975","title": "Editor(728)"}