{"color": "#FF3300","children": [{"color": "#FFFF00","children": [{"color": "#FFFF00","children": [{"color": "#CCCCCC","children": [{"color": "#FF3300","name": "RFC3643","title": "Fibre Channel (FC) Frame Encapsulation"},{"color": "#FF3300","name": "RFC4174","title": "The IPv4 Dynamic Host Configuration Protocol (DHCP) Option for the Internet Storage Name Service"},{"color": "#FF3300","name": "RFC4172","title": "iFCP - A Protocol for Internet Fibre Channel Storage Networking"},{"color": "#FF3300","name": "RFC4369","title": "Definitions of Managed Objects for Internet Fibre Channel Protocol (iFCP)"}],"name": "group0"}],"name": "C. Monia"},{"color": "#FFFF00","children": [{"color": "#CCCCCC","children": [{"color": "#FF3300","name": "RFC4174","title": "The IPv4 Dynamic Host Configuration Protocol (DHCP) Option for the Internet Storage Name Service"},{"color": "#FF3300","name": "RFC4369","title": "Definitions of Managed Objects for Internet Fibre Channel Protocol (iFCP)"},{"color": "#FF3300","name": "RFC3723","title": "Securing Block Storage Protocols over IP"},{"color": "#FF3300","name": "RFC4171","title": "Internet Storage Name Service (iSNS)"}],"name": "group0"}],"name": "J. Tseng"},{"color": "#FFFF00","children": [{"color": "#CCCCCC","children": [{"color": "#FF3300","name": "RFC4174","title": "The IPv4 Dynamic Host Configuration Protocol (DHCP) Option for the Internet Storage Name Service"},{"color": "#FF3300","name": "RFC4939","title": "Definitions of Managed Objects for iSNS (Internet Storage Name Service)"},{"color": "#FF3300","name": "RFC4369","title": "Definitions of Managed Objects for Internet Fibre Channel Protocol (iFCP)"},{"color": "#FF3300","name": "RFC4171","title": "Internet Storage Name Service (iSNS)"}],"name": "group0"}],"name": "K. Gibbons"}],"name": "authors"},{"color": "#33CC99","children": [{"color": "#FF6600","children": [{"color": "#33CC99","name": "RFC7146","title": "Securing Block Storage Protocols over IP: RFC 3723 Requirements Update for IPsec v3"}],"name": "updated"}],"name": "updatedBy"}],"name": "RFC4174","title": "The IPv4 Dynamic Host Configuration Protocol (DHCP) Option for the Internet Storage Name Service"}