{"color": "#FF3300","children": [{"color": "#FFFF00","children": [{"color": "#FFFF00","children": [{"color": "#CCCCCC","children": [{"color": "#FF3300","name": "RFC5789","title": "PATCH Method for HTTP"},{"color": "#FF3300","name": "RFC5657","title": "Guidance on Interoperation and Implementation Reports for Advancement to Draft Standard"},{"color": "#FF3300","name": "RFC4331","title": "Quota and Size Properties for Distributed Authoring and Versioning (DAV) Collections"},{"color": "#FF3300","name": "RFC4918","title": "Editor(707)"},{"color": "#FF3300","name": "RFC4791","title": "Calendaring Extensions to WebDAV (CalDAV)"}],"name": "group0"}],"name": "L. Dusseault"}],"name": "authors"},{"color": "#00FF00","children": [{"color": "#FF6600","children": [{"color": "#00FF00","name": "RFC2518","title": "HTTP Extensions for Distributed Authoring -- WEBDAV"}],"name": "obsoleteBy"}],"name": "obsolete"},{"color": "#33CC99","children": [{"color": "#FF6600","children": [{"color": "#33CC99","name": "RFC5689","title": "Extended MKCOL for Web Distributed Authoring and Versioning (WebDAV)"}],"name": "updated"}],"name": "updatedBy"}],"name": "RFC4918","title": "Editor(707)"}