{"color": "#FF3300","children": [{"color": "#FFFF00","children": [{"color": "#FFFF00","children": [{"color": "#CCCCCC","children": [{"color": "#FF3300","name": "RFC4665","title": "Editor(653)"}],"name": "group0"}],"name": "W. Augustyn"},{"color": "#FFFF00","children": [{"color": "#CCCCCC","children": [{"color": "#FF3300","name": "RFC4665","title": "Editor(653)"},{"color": "#FF3300","name": "RFC6246","title": "Editor(1030)"},{"color": "#FF3300","name": "RFC5501","title": "Editor(850)"}],"name": "group0"}],"name": "Y. Serbest"}],"name": "authors"}],"name": "RFC4665","title": "Editor(653)"}