{"color": "#FF3300","children": [{"color": "#FFFF00","children": [{"color": "#FFFF00","children": [{"color": "#CCCCCC","children": [{"color": "#FF3300","name": "RFC7545","title": "Editor(1326)"},{"color": "#FF3300","name": "RFC5349","title": "Elliptic Curve Cryptography (ECC) Support for Public Key Cryptography for Initial Authentication in Kerberos (PKINIT)"},{"color": "#FF3300","name": "RFC4178","title": "The Simple and Protected Generic Security Service Application Program Interface (GSS-API) Negotiation Mechanism"},{"color": "#FF3300","name": "RFC4757","title": "The RC4-HMAC Kerberos Encryption Types Used by Microsoft Windows"},{"color": "#FF3300","name": "RFC4121","title": "The Kerberos Version 5 Generic Security Service Application Program Interface (GSS-API) Mechanism: Version 2"},{"color": "#FF3300","name": "RFC6111","title": "Additional Kerberos Naming Constraints"},{"color": "#FF3300","name": "RFC4557","title": "Online Certificate Status Protocol (OCSP) Support for Public Key Cryptography for Initial Authentication in Kerberos (PKINIT)"},{"color": "#FF3300","name": "RFC6806","title": "Editor(1159)"},{"color": "#FF3300","name": "RFC6113","title": "A Generalized Framework for Kerberos Pre-Authentication"},{"color": "#FF3300","name": "RFC4559","title": "SPNEGO-based Kerberos and NTLM HTTP Authentication in Microsoft Windows"},{"color": "#FF3300","name": "RFC5929","title": "Channel Bindings for TLS"}],"name": "group0"},{"color": "#CCCCCC","children": [{"color": "#FF3300","name": "RFC4559","title": "SPNEGO-based Kerberos and NTLM HTTP Authentication in Microsoft Windows"}],"name": "group1"}],"name": "L. Zhu"},{"color": "#FFFF00","children": [{"color": "#CCCCCC","children": [{"color": "#FF3300","name": "RFC5349","title": "Elliptic Curve Cryptography (ECC) Support for Public Key Cryptography for Initial Authentication in Kerberos (PKINIT)"},{"color": "#FF3300","name": "RFC4178","title": "The Simple and Protected Generic Security Service Application Program Interface (GSS-API) Negotiation Mechanism"},{"color": "#FF3300","name": "RFC4757","title": "The RC4-HMAC Kerberos Encryption Types Used by Microsoft Windows"},{"color": "#FF3300","name": "RFC4121","title": "The Kerberos Version 5 Generic Security Service Application Program Interface (GSS-API) Mechanism: Version 2"},{"color": "#FF3300","name": "RFC4557","title": "Online Certificate Status Protocol (OCSP) Support for Public Key Cryptography for Initial Authentication in Kerberos (PKINIT)"},{"color": "#FF3300","name": "RFC4559","title": "SPNEGO-based Kerberos and NTLM HTTP Authentication in Microsoft Windows"},{"color": "#FF3300","name": "RFC4537","title": "Kerberos Cryptosystem Negotiation Extension"}],"name": "group0"}],"name": "K. Jaganathan"},{"color": "#FFFF00","children": [{"color": "#CCCCCC","children": [{"color": "#FF3300","name": "RFC6863","title": "Analysis of OSPF Security According to the Keying and Authentication for Routing Protocols (KARP) Design Guide"},{"color": "#FF3300","name": "RFC7056","title": "Name Attributes for the GSS-API Extensible Authentication Protocol (EAP) Mechanism"},{"color": "#FF3300","name": "RFC4120","title": "The Kerberos Network Authentication Service (V5)(541)"},{"color": "#FF3300","name": "RFC7474","title": "Editor(1310)"},{"color": "#FF3300","name": "RFC7211","title": "Operations Model for Router Keying"},{"color": "#FF3300","name": "RFC4121","title": "The Kerberos Version 5 Generic Security Service Application Program Interface (GSS-API) Mechanism: Version 2"},{"color": "#FF3300","name": "RFC5896","title": "Generic Security Service Application Program Interface (GSS-API): Delegate if Approved by Policy"},{"color": "#FF3300","name": "RFC7210","title": "Database of Long-Lived Symmetric Cryptographic Keys"},{"color": "#FF3300","name": "RFC6806","title": "Editor(1159)"},{"color": "#FF3300","name": "RFC4897","title": "Handling Normative References to Standards-Track Documents"},{"color": "#FF3300","name": "RFC6113","title": "A Generalized Framework for Kerberos Pre-Authentication"}],"name": "group0"},{"color": "#CCCCCC","children": [{"color": "#FF3300","name": "RFC4897","title": "Handling Normative References to Standards-Track Documents"}],"name": "group1"}],"name": "S. Hartman"}],"name": "authors"},{"color": "#33CC99","children": [{"color": "#FF6600","children": [{"color": "#33CC99","name": "RFC6112","title": "Anonymity Support for Kerberos"},{"color": "#33CC99","name": "RFC6542","title": "Kerberos Version 5 Generic Security Service Application Program Interface (GSS-API) Channel Binding Hash Agility"},{"color": "#33CC99","name": "RFC6649","title": "Deprecate DES, RC4-HMAC-EXP, and Other Weak Cryptographic Algorithms in Kerberos"}],"name": "updated"}],"name": "updatedBy"},{"color": "#CCCC99","children": [{"color": "#FF6600","children": [{"color": "#CCCC99","name": "RFC1964","title": "The Kerberos Version 5 GSS-API Mechanism"}],"name": "updatedBy"}],"name": "updated"}],"name": "RFC4121","title": "The Kerberos Version 5 Generic Security Service Application Program Interface (GSS-API) Mechanism: Version 2"}