{"color": "#FF3300","children": [{"color": "#FFFF00","children": [{"color": "#FFFF00","children": [{"color": "#CCCCCC","children": [{"color": "#FF3300","name": "RFC5054","title": "Using the Secure Remote Password (SRP) Protocol for TLS Authentication"}],"name": "group0"}],"name": "D. Taylor"},{"color": "#FFFF00","children": [{"color": "#CCCCCC","children": [{"color": "#FF3300","name": "RFC2945","title": "The SRP Authentication and Key Exchange System"},{"color": "#FF3300","name": "RFC2944","title": "Telnet Authentication: SRP"},{"color": "#FF3300","name": "RFC5054","title": "Using the Secure Remote Password (SRP) Protocol for TLS Authentication"}],"name": "group0"}],"name": "T. Wu"},{"color": "#FFFF00","children": [{"color": "#CCCCCC","children": [{"color": "#FF3300","name": "RFC5081","title": "Using OpenPGP Keys for Transport Layer Security (TLS) Authentication"},{"color": "#FF3300","name": "RFC6091","title": "Using OpenPGP Keys for Transport Layer Security (TLS) Authentication(998)"},{"color": "#FF3300","name": "RFC5054","title": "Using the Secure Remote Password (SRP) Protocol for TLS Authentication"}],"name": "group0"}],"name": "N. Mavrogiannopoulos"},{"color": "#FFFF00","children": [{"color": "#CCCCCC","children": [{"color": "#FF3300","name": "RFC5054","title": "Using the Secure Remote Password (SRP) Protocol for TLS Authentication"}],"name": "group0"}],"name": "T. Perrin"}],"name": "authors"}],"name": "RFC5054","title": "Using the Secure Remote Password (SRP) Protocol for TLS Authentication"}