{"color": "#FF3300","children": [{"color": "#FFFF00","children": [{"color": "#FFFF00","children": [{"color": "#CCCCCC","children": [{"color": "#FF3300","name": "RFC5236","title": "Improved Packet Reordering Metrics"}],"name": "group0"}],"name": "A. Jayasumana"},{"color": "#FFFF00","children": [{"color": "#CCCCCC","children": [{"color": "#FF3300","name": "RFC5236","title": "Improved Packet Reordering Metrics"}],"name": "group0"}],"name": "N. Piratla"},{"color": "#FFFF00","children": [{"color": "#CCCCCC","children": [{"color": "#FF3300","name": "RFC5236","title": "Improved Packet Reordering Metrics"}],"name": "group0"}],"name": "T. Banka"},{"color": "#FFFF00","children": [{"color": "#CCCCCC","children": [{"color": "#FF3300","name": "RFC5236","title": "Improved Packet Reordering Metrics"}],"name": "group0"}],"name": "A. Bare"},{"color": "#FFFF00","children": [{"color": "#CCCCCC","children": [{"color": "#FF3300","name": "RFC5236","title": "Improved Packet Reordering Metrics"}],"name": "group0"}],"name": "R. Whitner"}],"name": "authors"}],"name": "RFC5236","title": "Improved Packet Reordering Metrics"}