{"color": "#FF3300","children": [{"color": "#FFFF00","children": [{"color": "#FFFF00","children": [{"color": "#CCCCCC","children": [{"color": "#FF3300","name": "RFC5131","title": "Editor(765)"},{"color": "#FF3300","name": "RFC6226","title": "PIM Group-to-Rendezvous-Point Mapping"},{"color": "#FF3300","name": "RFC5132","title": "IP Multicast MIB"},{"color": "#FF3300","name": "RFC5060","title": "Protocol Independent Multicast MIB"},{"color": "#FF3300","name": "RFC5017","title": "Editor(733)"}],"name": "group0"}],"name": "D. McWalter"}],"name": "authors"}],"name": "RFC5017","title": "Editor(733)"}