{"color": "#FF3300","children": [{"color": "#FFFF00","children": [{"color": "#FFFF00","children": [{"color": "#CCCCCC","children": [{"color": "#FF3300","name": "RFC4268","title": "Entity State MIB"},{"color": "#FF3300","name": "RFC5674","title": "Alarms in Syslog"},{"color": "#FF3300","name": "RFC5277","title": "NETCONF Event Notifications"},{"color": "#FF3300","name": "RFC3877","title": "Alarm Management Information Base (MIB)"}],"name": "group0"}],"name": "S. Chisholm"},{"color": "#FFFF00","children": [{"color": "#CCCCCC","children": [{"color": "#FF3300","name": "RFC5424","title": "The Syslog Protocol"},{"color": "#FF3300","name": "RFC6012","title": "Datagram Transport Layer Security (DTLS) Transport Mapping for Syslog"},{"color": "#FF3300","name": "RFC5674","title": "Alarms in Syslog"},{"color": "#FF3300","name": "RFC6587","title": "Transmission of Syslog Messages over TCP"}],"name": "group0"}],"name": "R. Gerhards"}],"name": "authors"}],"name": "RFC5674","title": "Alarms in Syslog"}