{"color": "#FF3300","children": [{"color": "#FFFF00","children": [{"color": "#FFFF00","children": [{"color": "#CCCCCC","children": [{"color": "#FF3300","name": "RFC3069","title": "VLAN Aggregation for Efficient IP Address Allocation"},{"color": "#FF3300","name": "RFC4385","title": "Pseudowire Emulation Edge-to-Edge (PWE3) Control Word for Use over an MPLS PSN"},{"color": "#FF3300","name": "RFC3137","title": "OSPF Stub Router Advertisement"},{"color": "#FF3300","name": "RFC3308","title": "Layer Two Tunneling Protocol (L2TP) Differentiated Services Extension"},{"color": "#FF3300","name": "RFC5301","title": "Dynamic Hostname Exchange Mechanism for IS-IS(803)"},{"color": "#FF3300","name": "RFC5642","title": "Dynamic Hostname Exchange Mechanism for OSPF"},{"color": "#FF3300","name": "RFC5065","title": "Autonomous System Confederations for BGP(747)"},{"color": "#FF3300","name": "RFC6987","title": "OSPF Stub Router Advertisement(1198)"},{"color": "#FF3300","name": "RFC3277","title": "Intermediate System to Intermediate System (IS-IS) Transient Blackhole Avoidance"},{"color": "#FF3300","name": "RFC5311","title": "Editor(806)"},{"color": "#FF3300","name": "RFC3021","title": "Using 31-Bit Prefixes on IPv4 Point-to-Point Links"}],"name": "group0"},{"color": "#CCCCCC","children": [{"color": "#FF3300","name": "RFC5311","title": "Editor(806)"}],"name": "group1"}],"name": "D. McPherson"},{"color": "#FFFF00","children": [{"color": "#CCCCCC","children": [{"color": "#FF3300","name": "RFC3906","title": "Calculating Interior Gateway Protocol (IGP) Routes Over Traffic Engineering Tunnels"},{"color": "#FF3300","name": "RFC2763","title": "Dynamic Hostname Exchange Mechanism for IS-IS"},{"color": "#FF3300","name": "RFC5301","title": "Dynamic Hostname Exchange Mechanism for IS-IS(803)"},{"color": "#FF3300","name": "RFC5120","title": "M-ISIS: Multi Topology (MT) Routing in Intermediate System to Intermediate Systems (IS-ISs)"},{"color": "#FF3300","name": "RFC5309","title": "Editor(805)"},{"color": "#FF3300","name": "RFC5837","title": "Editor(943)"},{"color": "#FF3300","name": "RFC4970","title": "Editor(725)"},{"color": "#FF3300","name": "RFC4971","title": "Editor(726)"}],"name": "group0"}],"name": "N. Shen"}],"name": "authors"},{"color": "#00FF00","children": [{"color": "#FF6600","children": [{"color": "#00FF00","name": "RFC2763","title": "Dynamic Hostname Exchange Mechanism for IS-IS"}],"name": "obsoleteBy"}],"name": "obsolete"},{"color": "#33CC99","children": [{"color": "#FF6600","children": [{"color": "#33CC99","name": "RFC6232","title": "Purge Originator Identification TLV for IS-IS"}],"name": "updated"}],"name": "updatedBy"}],"name": "RFC5301","title": "Dynamic Hostname Exchange Mechanism for IS-IS(803)"}