{"color": "#FF3300","children": [{"color": "#FFFF00","children": [{"color": "#FFFF00","children": [{"color": "#CCCCCC","children": [{"color": "#FF3300","name": "RFC6254","title": "Request to Move RFC 2754 to Historic Status"}],"name": "group0"}],"name": "M. McFadden"}],"name": "authors"},{"color": "#00FF00","children": [{"color": "#FF6600","children": [{"color": "#00FF00","name": "RFC2754","title": "RPS IANA Issues"}],"name": "obsoleteBy"}],"name": "obsolete"}],"name": "RFC6254","title": "Request to Move RFC 2754 to Historic Status"}