{"color": "#FF3300","children": [{"color": "#FFFF00","children": [{"color": "#FFFF00","children": [{"color": "#CCCCCC","children": [{"color": "#FF3300","name": "RFC7089","title": "HTTP Framework for Time-Based Access to Resource States -- Memento"},{"color": "#FF3300","name": "RFC4452","title": "The \"info\" URI Scheme for Information Assets with Identifiers in Public Namespaces"}],"name": "group0"}],"name": "H. Van de Sompel"},{"color": "#FFFF00","children": [{"color": "#CCCCCC","children": [{"color": "#FF3300","name": "RFC7089","title": "HTTP Framework for Time-Based Access to Resource States -- Memento"}],"name": "group0"}],"name": "M. Nelson"},{"color": "#FFFF00","children": [{"color": "#CCCCCC","children": [{"color": "#FF3300","name": "RFC7089","title": "HTTP Framework for Time-Based Access to Resource States -- Memento"}],"name": "group0"}],"name": "R. Sanderson"}],"name": "authors"}],"name": "RFC7089","title": "HTTP Framework for Time-Based Access to Resource States -- Memento"}