{"color": "#FF3300","children": [{"color": "#FFFF00","children": [{"color": "#FFFF00","children": [{"color": "#CCCCCC","children": [{"color": "#FF3300","name": "RFC6879","title": "IPv6 Enterprise Network Renumbering Scenarios, Considerations, and Methods"},{"color": "#FF3300","name": "RFC7010","title": "IPv6 Site Renumbering Gap Analysis"}],"name": "group0"}],"name": "B. Liu"},{"color": "#FFFF00","children": [{"color": "#CCCCCC","children": [{"color": "#FF3300","name": "RFC6879","title": "IPv6 Enterprise Network Renumbering Scenarios, Considerations, and Methods"},{"color": "#FF3300","name": "RFC6436","title": "Rationale for Update to the IPv6 Flow Label Specification"},{"color": "#FF3300","name": "RFC7045","title": "Transmission and Processing of IPv6 Extension Headers"},{"color": "#FF3300","name": "RFC6930","title": "Editor(1183)"},{"color": "#FF3300","name": "RFC6036","title": "Emerging Service Provider Scenarios for IPv6 Deployment"},{"color": "#FF3300","name": "RFC7098","title": "Using the IPv6 Flow Label for Load Balancing in Server Farms"},{"color": "#FF3300","name": "RFC6273","title": "The Secure Neighbor Discovery (SEND) Hash Threat Analysis"},{"color": "#FF3300","name": "RFC7136","title": "Significance of IPv6 Interface Identifiers"},{"color": "#FF3300","name": "RFC7421","title": "Editor(1295)"},{"color": "#FF3300","name": "RFC6751","title": "Editor(1147)"},{"color": "#FF3300","name": "RFC6264","title": "An Incremental Carrier-Grade NAT (CGN) for IPv6 Transition"}],"name": "group0"},{"color": "#CCCCCC","children": [{"color": "#FF3300","name": "RFC6751","title": "Editor(1147)"}],"name": "group1"}],"name": "S. Jiang"},{"color": "#FFFF00","children": [{"color": "#CCCCCC","children": [{"color": "#FF3300","name": "RFC5887","title": "Renumbering Still Needs Work"},{"color": "#FF3300","name": "RFC2768","title": "Network Policy and Services: A Report of a Workshop on Middleware"},{"color": "#FF3300","name": "RFC6438","title": "Using the IPv6 Flow Label for Equal Cost Multipath Routing and Link Aggregation in Tunnels"},{"color": "#FF3300","name": "RFC6879","title": "IPv6 Enterprise Network Renumbering Scenarios, Considerations, and Methods"},{"color": "#FF3300","name": "RFC3234","title": "Middleboxes: Taxonomy and Issues"},{"color": "#FF3300","name": "RFC3140","title": "Per Hop Behavior Identification Codes(378)"},{"color": "#FF3300","name": "RFC4775","title": "Editor(672)"},{"color": "#FF3300","name": "RFC7526","title": "Editor(1317)"},{"color": "#FF3300","name": "RFC2529","title": "Transmission of IPv6 over IPv4 Domains without Explicit Tunnels"},{"color": "#FF3300","name": "RFC3086","title": "Definition of Differentiated Services Per Domain Behaviors and Rules for their Specification"},{"color": "#FF3300","name": "RFC6436","title": "Rationale for Update to the IPv6 Flow Label Specification"}],"name": "group0"},{"color": "#CCCCCC","children": [{"color": "#FF3300","name": "RFC3086","title": "Definition of Differentiated Services Per Domain Behaviors and Rules for their Specification"}],"name": "group1"}],"name": "B. Carpenter"},{"color": "#FFFF00","children": [{"color": "#CCCCCC","children": [{"color": "#FF3300","name": "RFC4578","title": "Editor(641)"},{"color": "#FF3300","name": "RFC6807","title": "Population Count Extensions to Protocol Independent Multicast (PIM)"},{"color": "#FF3300","name": "RFC5059","title": "Bootstrap Router (BSR) Mechanism for Protocol Independent Multicast (PIM)"},{"color": "#FF3300","name": "RFC6614","title": "Transport Layer Security (TLS) Encryption for RADIUS"},{"color": "#FF3300","name": "RFC6104","title": "Rogue IPv6 Router Advertisement Problem Statement"},{"color": "#FF3300","name": "RFC4076","title": "Renumbering Requirements for Stateless Dynamic Host Configuration Protocol for IPv6 (DHCPv6)"},{"color": "#FF3300","name": "RFC6831","title": "The Locator\/ID Separation Protocol (LISP) for Multicast Environments"},{"color": "#FF3300","name": "RFC6450","title": "Multicast Ping Protocol"},{"color": "#FF3300","name": "RFC6559","title": "A Reliable Transport Mechanism for PIM"},{"color": "#FF3300","name": "RFC6395","title": "An Interface Identifier (ID) Hello Option for PIM"},{"color": "#FF3300","name": "RFC4242","title": "Information Refresh Time Option for Dynamic Host Configuration Protocol for IPv6 (DHCPv6)"}],"name": "group0"},{"color": "#CCCCCC","children": [{"color": "#FF3300","name": "RFC6395","title": "An Interface Identifier (ID) Hello Option for PIM"}],"name": "group1"}],"name": "S. Venaas"},{"color": "#FFFF00","children": [{"color": "#CCCCCC","children": [{"color": "#FF3300","name": "RFC7439","title": "Editor(1303)"},{"color": "#FF3300","name": "RFC6540","title": "IPv6 Support Required for All IP-Capable Nodes"},{"color": "#FF3300","name": "RFC6547","title": "RFC 3627 to Historic Status"},{"color": "#FF3300","name": "RFC7010","title": "IPv6 Site Renumbering Gap Analysis"},{"color": "#FF3300","name": "RFC7527","title": "Enhanced Duplicate Address Detection"},{"color": "#FF3300","name": "RFC6640","title": "IETF Meeting Attendees' Frequently Asked (Travel) Questions"}],"name": "group0"}],"name": "W. George"}],"name": "authors"}],"name": "RFC7010","title": "IPv6 Site Renumbering Gap Analysis"}